kronoterm2mqtt/__init__.py
kronoterm2mqtt/__main__.py
kronoterm2mqtt/api.py
kronoterm2mqtt/constants.py
kronoterm2mqtt/expander.py
kronoterm2mqtt/mqtt_handler.py
kronoterm2mqtt/user_settings.py
kronoterm2mqtt/cli_app/__init__.py
kronoterm2mqtt/cli_app/print-values.py
kronoterm2mqtt/cli_app/publish-loop.py
kronoterm2mqtt/cli_app/publish.py~
kronoterm2mqtt/cli_app/settings.py
kronoterm2mqtt/cli_app/settings.py~
kronoterm2mqtt/cli_app/systemd.py
kronoterm2mqtt/cli_dev/__init__.py
kronoterm2mqtt/cli_dev/code_style.py
kronoterm2mqtt/cli_dev/expander.py
kronoterm2mqtt/cli_dev/firmware.py
kronoterm2mqtt/cli_dev/packaging.py
kronoterm2mqtt/cli_dev/testing.py
kronoterm2mqtt/cli_dev/update_readme_history.py
kronoterm2mqtt/definitions/kronoterm_ksm.toml
kronoterm2mqtt/definitions/kronoterm_ksm.toml~
kronoterm2mqtt/definitions/kronoterm_wpg.toml
kronoterm2mqtt/examples/dashboard-overview.yaml
kronoterm2mqtt/examples/expander.py
kronoterm2mqtt/examples/print-temperatures.py
kronoterm2mqtt/tests/__init__.py
kronoterm2mqtt/tests/test_cli.py
kronoterm2mqtt/tests/test_doctests.py
kronoterm2mqtt/tests/test_project_setup.py
kronoterm2mqtt/tests/test_readme.py
kronoterm2mqtt/tests/test_readme_history.py
kronoterm2mqtt/tests/test_user_settings.py
kronoterm2mqtt-0.1.16.dist-info/METADATA
kronoterm2mqtt-0.1.16.dist-info/WHEEL
kronoterm2mqtt-0.1.16.dist-info/entry_points.txt
kronoterm2mqtt-0.1.16.dist-info/licenses/LICENSE
kronoterm2mqtt-0.1.16.dist-info/RECORD
