Metadata-Version: 2.4
Name: kronoterm2mqtt
Version: 0.1.16
Summary: Sends MQTT events from KRONOTERM heat pump
Project-URL: Documentation, https://github.com/kosl/kronoterm2mqtt
Project-URL: Source, https://github.com/kosl/kronoterm2mqtt
Author-email: Leon Kos <leon.kos@lecad.fs.uni-lj.si>
License-Expression: GPL-3.0-or-later
License-File: LICENSE
Requires-Python: <4,>=3.11
Requires-Dist: bx-py-utils
Requires-Dist: cli-base-utilities>=0.17.0
Requires-Dist: ha-services>=2.10.0
Requires-Dist: pymodbus[serial]>=3.10.0
Requires-Dist: rich
Requires-Dist: tyro
